aws_jmespath_utils/__init__.py
aws_jmespath_utils/common.py
aws_jmespath_utils/filter_tags.py
aws_jmespath_utils-1.1.0.dist-info/LICENSE
aws_jmespath_utils-1.1.0.dist-info/WHEEL
aws_jmespath_utils-1.1.0.dist-info/METADATA
aws_jmespath_utils-1.1.0.dist-info/RECORD
